pipedream_solver/geometry.py
pipedream_solver/hydraulics.py
pipedream_solver/hydrology.py
pipedream_solver/infiltration.py
pipedream_solver/ngeometry.py
pipedream_solver/ninfiltration.py
pipedream_solver/nquality.py
pipedream_solver/nsuperlink.py
pipedream_solver/nutils.py
pipedream_solver/simulation.py
pipedream_solver/storage.py
pipedream_solver/superlink.py
pipedream_solver/transport.py
pipedream_solver/utils.py
pipedream_solver/visualization.py
pipedream_solver-0.2.2.dist-info/LICENSE
pipedream_solver-0.2.2.dist-info/METADATA
pipedream_solver-0.2.2.dist-info/WHEEL
pipedream_solver-0.2.2.dist-info/top_level.txt
pipedream_solver-0.2.2.dist-info/RECORD
